vision_utils/__init__.py
vision_utils/boxutils.py
vision_utils/generic_utils.py
vision_utils-0.1.1.dist-info/METADATA
vision_utils-0.1.1.dist-info/WHEEL
vision_utils-0.1.1.dist-info/top_level.txt
vision_utils-0.1.1.dist-info/RECORD
